Header:
	Main Program:	8
	List Constants size:	6
	List class size:	8
	Size bytecode:	51
Constants:
		type:	5
		UID:1
		String:	(3)i +
		type:	5
		UID:2
		String:	(6)Merda?
		type:	5
		UID:3
		String:	(4)hola
		type:	3
		UID:4
		Integer:	0
		type:	3
		UID:5
		Integer:	100000
		type:	5
		UID:6
		String:	(19)Main del Hola Mon! 
Class:
	UID:	1
	FatherUID:	0
	native?:	1
	name:	(7)Object
	Propieties (0):
	Methods (0):
	UID:	2
	FatherUID:	1
	native?:	1
	name:	(8)Boolean
	Propieties (0):
	Methods (3):
		UID:	1
		ByteCodeLine:	0
		Constructor:	0
		static?:	1
		Name:	(15)Boolean(Object)
		UID:	2
		ByteCodeLine:	0
		Constructor:	0
		static?:	0
		Name:	(12)and(Boolean)
		UID:	3
		ByteCodeLine:	0
		Constructor:	0
		static?:	0
		Name:	(11)or(Boolean)
	UID:	3
	FatherUID:	1
	native?:	1
	name:	(8)Integer
	Propieties (0):
	Methods (13):
		UID:	2
		ByteCodeLine:	0
		Constructor:	0
		static?:	1
		Name:	(15)Integer(Object)
		UID:	3
		ByteCodeLine:	0
		Constructor:	1
		static?:	0
		Name:	(15)Integer(String)
		UID:	4
		ByteCodeLine:	0
		Constructor:	0
		static?:	0
		Name:	(3)inc
		UID:	5
		ByteCodeLine:	0
		Constructor:	0
		static?:	0
		Name:	(3)dec
		UID:	6
		ByteCodeLine:	0
		Constructor:	0
		static?:	0
		Name:	(12)add(Integer)
		UID:	7
		ByteCodeLine:	0
		Constructor:	0
		static?:	0
		Name:	(12)sub(Integer)
		UID:	8
		ByteCodeLine:	0
		Constructor:	0
		static?:	0
		Name:	(12)mul(Integer)
		UID:	9
		ByteCodeLine:	0
		Constructor:	0
		static?:	0
		Name:	(12)div(Integer)
		UID:	10
		ByteCodeLine:	0
		Constructor:	0
		static?:	0
		Name:	(12)dif(Integer)
		UID:	11
		ByteCodeLine:	0
		Constructor:	0
		static?:	0
		Name:	(14)equal(Integer)
		UID:	12
		ByteCodeLine:	0
		Constructor:	0
		static?:	0
		Name:	(14)lower(Integer)
		UID:	13
		ByteCodeLine:	0
		Constructor:	0
		static?:	0
		Name:	(16)greater(Integer)
		UID:	14
		ByteCodeLine:	0
		Constructor:	0
		static?:	0
		Name:	(8)toString
	UID:	4
	FatherUID:	1
	native?:	1
	name:	(7)String
	Propieties (0):
	Methods (7):
		UID:	3
		ByteCodeLine:	0
		Constructor:	0
		static?:	1
		Name:	(14)String(Object)
		UID:	4
		ByteCodeLine:	0
		Constructor:	0
		static?:	0
		Name:	(11)add(String)
		UID:	5
		ByteCodeLine:	0
		Constructor:	0
		static?:	0
		Name:	(14)sufix(Integer)
		UID:	6
		ByteCodeLine:	0
		Constructor:	0
		static?:	0
		Name:	(15)prefix(Integer)
		UID:	7
		ByteCodeLine:	0
		Constructor:	0
		static?:	0
		Name:	(27)substring(Integer, Integer)
		UID:	8
		ByteCodeLine:	0
		Constructor:	0
		static?:	0
		Name:	(6)length
		UID:	9
		ByteCodeLine:	0
		Constructor:	0
		static?:	0
		Name:	(13)split(String)
	UID:	5
	FatherUID:	1
	native?:	1
	name:	(5)List
	Propieties (0):
	Methods (10):
		UID:	4
		ByteCodeLine:	0
		Constructor:	0
		static?:	1
		Name:	(12)List(Object)
		UID:	5
		ByteCodeLine:	0
		Constructor:	1
		static?:	0
		Name:	(4)List
		UID:	6
		ByteCodeLine:	0
		Constructor:	0
		static?:	0
		Name:	(12)get(Integer)
		UID:	7
		ByteCodeLine:	0
		Constructor:	0
		static?:	0
		Name:	(6)length
		UID:	8
		ByteCodeLine:	0
		Constructor:	0
		static?:	0
		Name:	(11)add(Object)
		UID:	9
		ByteCodeLine:	0
		Constructor:	0
		static?:	0
		Name:	(16)addFirst(Object)
		UID:	10
		ByteCodeLine:	0
		Constructor:	0
		static?:	0
		Name:	(5)first
		UID:	11
		ByteCodeLine:	0
		Constructor:	0
		static?:	0
		Name:	(11)removeFirst
		UID:	12
		ByteCodeLine:	0
		Constructor:	0
		static?:	0
		Name:	(4)last
		UID:	13
		ByteCodeLine:	0
		Constructor:	0
		static?:	0
		Name:	(3)pop
	UID:	6
	FatherUID:	1
	native?:	1
	name:	(5)File
	Propieties (0):
	Methods (8):
		UID:	5
		ByteCodeLine:	0
		Constructor:	0
		static?:	1
		Name:	(12)File(Object)
		UID:	6
		ByteCodeLine:	0
		Constructor:	1
		static?:	0
		Name:	(20)File(String, String)
		UID:	7
		ByteCodeLine:	0
		Constructor:	0
		static?:	0
		Name:	(13)write(String)
		UID:	8
		ByteCodeLine:	0
		Constructor:	0
		static?:	0
		Name:	(4)read
		UID:	9
		ByteCodeLine:	0
		Constructor:	0
		static?:	0
		Name:	(4)isOk
		UID:	10
		ByteCodeLine:	0
		Constructor:	0
		static?:	0
		Name:	(3)eof
		UID:	11
		ByteCodeLine:	0
		Constructor:	0
		static?:	0
		Name:	(9)errorCode
		UID:	12
		ByteCodeLine:	0
		Constructor:	0
		static?:	0
		Name:	(5)error
	UID:	7
	FatherUID:	1
	native?:	1
	name:	(6)Shell
	Propieties (0):
	Methods (4):
		UID:	6
		ByteCodeLine:	0
		Constructor:	0
		static?:	1
		Name:	(13)Shell(Object)
		UID:	7
		ByteCodeLine:	0
		Constructor:	0
		static?:	0
		Name:	(14)stdout(String)
		UID:	8
		ByteCodeLine:	0
		Constructor:	0
		static?:	0
		Name:	(5)stdin
		UID:	9
		ByteCodeLine:	0
		Constructor:	0
		static?:	0
		Name:	(14)stderr(String)
	UID:	8
	FatherUID:	1
	native?:	0
	name:	(11)helloWorld
	Propieties (0):
	Methods (3):
		UID:	7
		ByteCodeLine:	0
		Constructor:	0
		static?:	1
		Name:	(18)helloWorld(Object)
		UID:	8
		ByteCodeLine:	2
		Constructor:	1
		static?:	0
		Name:	(10)helloWorld
		UID:	9
		ByteCodeLine:	14
		Constructor:	0
		static?:	0
		Name:	(4)main
ByteCode:
	0:RET	-2	
	1:SIZE_INSTRUCTIONS	7	
	2:LOAD_CLASS	7	(Shell)
	3:LOAD_METHOD	7	(stdout(String))
	4:LOAD_CONSTANT	1	(i +)
	5:CALL	1	(stdout(String))
	6:POP_TOP	0	
	7:LOAD_CLASS	7	(Shell)
	8:LOAD_METHOD	7	(stdout(String))
	9:LOAD_CONSTANT	2	(Merda?)
	10:CALL	1	(stdout(String))
	11:POP_TOP	0	
	12:RET	0	
	13:SIZE_INSTRUCTIONS	8	
	14:PUSH_TOP	0	(reservant:i)
	15:LOAD_CLASS	7	(Shell)
	16:LOAD_METHOD	7	(stdout(String))
	17:LOAD_CONSTANT	3	(hola)
	18:CALL	1	(stdout(String))
	19:POP_TOP	0	
	20:LOAD_CONSTANT	4	(0)
	21:STORE_PRIVATE	1	
	22:LOAD_CLASS	7	(Shell)
	23:LOAD_METHOD	7	(stdout(String))
	24:LOAD_PRIVATE	1	(i)
	25:LOAD_METHOD	14	(toString)
	26:CALL	0	(toString)
	27:CALL	1	(stdout(String))
	28:POP_TOP	0	
	29:LOAD_PRIVATE	1	(i)
	30:LOAD_METHOD	12	(lower(Integer))
	31:LOAD_CONSTANT	5	(100000)
	32:CALL	1	(lower(Integer))
	33:GOTO_FALSE	39	
	34:LOAD_PRIVATE	1	(i)
	35:LOAD_METHOD	4	(inc)
	36:CALL	0	(inc)
	37:POP_TOP	0	
	38:GOTO	29	
	39:LOAD_CLASS	7	(Shell)
	40:LOAD_METHOD	7	(stdout(String))
	41:LOAD_CONSTANT	6	(Main del Hola Mon! )
	42:LOAD_METHOD	4	(add(String))
	43:LOAD_PRIVATE	1	(i)
	44:LOAD_METHOD	14	(toString)
	45:CALL	0	(toString)
	46:CALL	1	(add(String))
	47:CALL	1	(stdout(String))
	48:POP_TOP	0	
	49:RET	-2	
	50:SIZE_INSTRUCTIONS	9	
